{"problem":{"V":100,"A":[{"src":1,"dst":2,"cost":9.840802052499892,"toll":true},{"src":1,"dst":21,"cost":9.699526626859235,"toll":false},{"src":1,"dst":74,"cost":9.691156828602299,"toll":true},{"src":1,"dst":76,"cost":20.234432281315712,"toll":false},{"src":1,"dst":93,"cost":4.06157731046561,"toll":true},{"src":1,"dst":94,"cost":19.530658177194063,"toll":false},{"src":1,"dst":95,"cost":19.530273645812834,"toll":false},{"src":1,"dst":96,"cost":35.0,"toll":false},{"src":2,"dst":1,"cost":9.840802052499892,"toll":true},{"src":2,"dst":93,"cost":25.37356788492537,"toll":false},{"src":2,"dst":96,"cost":30.04448510622299,"toll":false},{"src":2,"dst":97,"cost":28.739338967430996,"toll":false},{"src":2,"dst":99,"cost":22.697143203431597,"toll":false},{"src":2,"dst":100,"cost":31.70588413457027,"toll":false},{"src":3,"dst":4,"cost":35.0,"toll":false},{"src":3,"dst":5,"cost":19.966891292581657,"toll":false},{"src":3,"dst":42,"cost":29.04659851130385,"toll":false},{"src":3,"dst":46,"cost":28.699372029704282,"toll":false},{"src":3,"dst":47,"cost":9.903373070793208,"toll":true},{"src":3,"dst":48,"cost":7.576173403689467,"toll":false},{"src":3,"dst":50,"cost":10.26216828740564,"toll":false},{"src":4,"dst":3,"cost":35.0,"toll":false},{"src":4,"dst":10,"cost":32.54081801595355,"toll":false},{"src":4,"dst":47,"cost":12.787859295521681,"toll":true},{"src":4,"dst":48,"cost":35.0,"toll":false},{"src":4,"dst":49,"cost":10.257452266926434,"toll":false},{"src":5,"dst":3,"cost":19.966891292581657,"toll":false},{"src":5,"dst":41,"cost":26.255929701754496,"toll":false},{"src":5,"dst":42,"cost":6.632936398629157,"toll":false},{"src":5,"dst":43,"cost":22.88060619247216,"toll":false},{"src":5,"dst":44,"cost":21.340626323174,"toll":false},{"src":5,"dst":46,"cost":26.00701457513923,"toll":false},{"src":6,"dst":7,"cost":10.7138807397607,"toll":false},{"src":6,"dst":32,"cost":31.1118738041461,"toll":false},{"src":6,"dst":33,"cost":35.0,"toll":false},{"src":6,"dst":34,"cost":32.888304871476905,"toll":false},{"src":6,"dst":35,"cost":34.609321679610645,"toll":false},{"src":7,"dst":6,"cost":10.7138807397607,"toll":false},{"src":7,"dst":32,"cost":32.84178353398863,"toll":false},{"src":7,"dst":35,"cost":28.258143617324027,"toll":false},{"src":7,"dst":36,"cost":23.917541920932145,"toll":false},{"src":7,"dst":43,"cost":17.5,"toll":true},{"src":8,"dst":50,"cost":29.150978712283905,"toll":false},{"src":8,"dst":53,"cost":34.950903653677244,"toll":false},{"src":8,"dst":54,"cost":17.66218958147799,"toll":false},{"src":8,"dst":55,"cost":34.17976555468401,"toll":false},{"src":8,"dst":62,"cost":25.63524408454809,"toll":false},{"src":9,"dst":10,"cost":13.644745762901852,"toll":false},{"src":9,"dst":48,"cost":23.298744235960914,"toll":false},{"src":9,"dst":49,"cost":33.14125491311384,"toll":false},{"src":9,"dst":50,"cost":35.0,"toll":false},{"src":9,"dst":53,"cost":35.0,"toll":false},{"src":10,"dst":4,"cost":32.54081801595355,"toll":false},{"src":10,"dst":9,"cost":13.644745762901852,"toll":false},{"src":10,"dst":24,"cost":15.353665331122379,"toll":false},{"src":10,"dst":47,"cost":7.536911110051758,"toll":false},{"src":10,"dst":49,"cost":20.916918223558433,"toll":false},{"src":11,"dst":13,"cost":11.030714015685177,"toll":true},{"src":11,"dst":56,"cost":8.339171194745601,"toll":false},{"src":11,"dst":57,"cost":23.67420589544997,"toll":false},{"src":11,"dst":58,"cost":13.92653318101821,"toll":false},{"src":11,"dst":59,"cost":10.592783165038856,"toll":false},{"src":11,"dst":80,"cost":33.2113158010213,"toll":false},{"src":11,"dst":89,"cost":3.384094479168793,"toll":true},{"src":12,"dst":63,"cost":17.5,"toll":true},{"src":12,"dst":66,"cost":20.64206348466726,"toll":false},{"src":12,"dst":67,"cost":10.473561851245949,"toll":false},{"src":12,"dst":72,"cost":23.341058763214626,"toll":false},{"src":13,"dst":11,"cost":11.030714015685177,"toll":true},{"src":13,"dst":59,"cost":12.355113618068966,"toll":true},{"src":13,"dst":68,"cost":4.633325728262582,"toll":true},{"src":13,"dst":69,"cost":5.251873009631446,"toll":true},{"src":13,"dst":70,"cost":34.939550234423976,"toll":false},{"src":13,"dst":80,"cost":3.8669285466641714,"toll":true},{"src":14,"dst":15,"cost":10.992807878634057,"toll":false},{"src":14,"dst":20,"cost":9.21423236307159,"toll":false},{"src":14,"dst":67,"cost":11.625878279116964,"toll":false},{"src":14,"dst":71,"cost":35.0,"toll":false},{"src":14,"dst":73,"cost":18.62612772518185,"toll":false},{"src":15,"dst":14,"cost":10.992807878634057,"toll":false},{"src":15,"dst":16,"cost":6.719225791967787,"toll":false},{"src":15,"dst":20,"cost":35.0,"toll":false},{"src":15,"dst":73,"cost":29.688421543116917,"toll":false},{"src":16,"dst":15,"cost":6.719225791967787,"toll":false},{"src":16,"dst":20,"cost":18.412497470245427,"toll":false},{"src":16,"dst":73,"cost":11.482153410570735,"toll":false},{"src":16,"dst":74,"cost":33.42320001685904,"toll":false},{"src":16,"dst":75,"cost":2.557757402889405,"toll":true},{"src":16,"dst":77,"cost":5.209917287303246,"toll":true},{"src":16,"dst":79,"cost":19.333252965211408,"toll":false},{"src":17,"dst":40,"cost":27.248695041643977,"toll":false},{"src":17,"dst":56,"cost":27.168879045790447,"toll":false},{"src":17,"dst":81,"cost":22.57035180236781,"toll":false},{"src":17,"dst":89,"cost":35.0,"toll":false},{"src":18,"dst":31,"cost":34.62645493677499,"toll":false},{"src":18,"dst":32,"cost":14.727623618553261,"toll":true},{"src":18,"dst":36,"cost":8.736878791247403,"toll":false},{"src":18,"dst":39,"cost":25.62298101753235,"toll":false},{"src":19,"dst":31,"cost":35.0,"toll":false},{"src":19,"dst":32,"cost":35.0,"toll":false},{"src":19,"dst":38,"cost":22.88810981059121,"toll":false},{"src":19,"dst":82,"cost":6.471042753087826,"toll":true},{"src":19,"dst":84,"cost":33.92886600921691,"toll":false},{"src":19,"dst":85,"cost":12.06161084561668,"toll":false},{"src":19,"dst":90,"cost":19.401306478002173,"toll":false},{"src":20,"dst":14,"cost":9.21423236307159,"toll":false},{"src":20,"dst":15,"cost":35.0,"toll":false},{"src":20,"dst":16,"cost":18.412497470245427,"toll":false},{"src":20,"dst":64,"cost":24.677027371758307,"toll":false},{"src":20,"dst":67,"cost":24.284829505478324,"toll":false},{"src":20,"dst":75,"cost":35.0,"toll":false},{"src":21,"dst":1,"cost":9.699526626859235,"toll":false},{"src":21,"dst":74,"cost":20.385068847385323,"toll":false},{"src":21,"dst":77,"cost":28.053694293617223,"toll":false},{"src":21,"dst":96,"cost":6.820495698080055,"toll":false},{"src":21,"dst":97,"cost":9.416427859406491,"toll":false},{"src":22,"dst":23,"cost":9.774730343202027,"toll":true},{"src":22,"dst":25,"cost":35.0,"toll":false},{"src":22,"dst":26,"cost":35.0,"toll":false},{"src":22,"dst":27,"cost":3.22411542363312,"toll":true},{"src":22,"dst":28,"cost":13.904596866554709,"toll":false},{"src":23,"dst":22,"cost":9.774730343202027,"toll":true},{"src":23,"dst":24,"cost":4.687636675714602,"toll":true},{"src":23,"dst":26,"cost":8.41325769560465,"toll":false},{"src":23,"dst":28,"cost":31.57715521163329,"toll":false},{"src":24,"dst":10,"cost":15.353665331122379,"toll":false},{"src":24,"dst":23,"cost":4.687636675714602,"toll":true},{"src":24,"dst":26,"cost":35.0,"toll":false},{"src":24,"dst":47,"cost":6.852669942383832,"toll":true},{"src":25,"dst":22,"cost":35.0,"toll":false},{"src":25,"dst":26,"cost":35.0,"toll":false},{"src":25,"dst":27,"cost":24.467357468037417,"toll":false},{"src":25,"dst":35,"cost":23.38633693485915,"toll":false},{"src":25,"dst":43,"cost":26.524750265624778,"toll":false},{"src":25,"dst":44,"cost":25.610963019187672,"toll":false},{"src":25,"dst":45,"cost":18.455277092911057,"toll":false},{"src":26,"dst":22,"cost":35.0,"toll":false},{"src":26,"dst":23,"cost":8.41325769560465,"toll":false},{"src":26,"dst":24,"cost":35.0,"toll":false},{"src":26,"dst":25,"cost":35.0,"toll":false},{"src":26,"dst":45,"cost":35.0,"toll":false},{"src":26,"dst":46,"cost":17.097977369783646,"toll":false},{"src":26,"dst":47,"cost":19.151819543392744,"toll":false},{"src":27,"dst":22,"cost":3.22411542363312,"toll":true},{"src":27,"dst":25,"cost":24.467357468037417,"toll":false},{"src":27,"dst":28,"cost":30.07959039801434,"toll":false},{"src":27,"dst":29,"cost":13.9546427552345,"toll":true},{"src":27,"dst":34,"cost":30.039700946531426,"toll":false},{"src":27,"dst":35,"cost":14.085476690181842,"toll":false},{"src":28,"dst":22,"cost":13.904596866554709,"toll":false},{"src":28,"dst":23,"cost":31.57715521163329,"toll":false},{"src":28,"dst":27,"cost":30.07959039801434,"toll":false},{"src":28,"dst":29,"cost":16.63744444993812,"toll":true},{"src":29,"dst":27,"cost":13.9546427552345,"toll":true},{"src":29,"dst":28,"cost":16.63744444993812,"toll":true},{"src":29,"dst":30,"cost":20.502632398154347,"toll":false},{"src":29,"dst":34,"cost":35.0,"toll":false},{"src":29,"dst":93,"cost":6.342880324826749,"toll":true},{"src":29,"dst":100,"cost":8.293140096788402,"toll":true},{"src":30,"dst":29,"cost":20.502632398154347,"toll":false},{"src":30,"dst":33,"cost":14.749311938227134,"toll":false},{"src":30,"dst":34,"cost":32.29383331673259,"toll":false},{"src":30,"dst":83,"cost":8.471127521034486,"toll":false},{"src":30,"dst":93,"cost":19.50758331929983,"toll":false},{"src":31,"dst":18,"cost":34.62645493677499,"toll":false},{"src":31,"dst":19,"cost":35.0,"toll":false},{"src":31,"dst":32,"cost":35.0,"toll":false},{"src":31,"dst":38,"cost":35.0,"toll":false},{"src":31,"dst":39,"cost":6.261212384924658,"toll":false},{"src":32,"dst":6,"cost":31.1118738041461,"toll":false},{"src":32,"dst":7,"cost":32.84178353398863,"toll":false},{"src":32,"dst":18,"cost":14.727623618553261,"toll":true},{"src":32,"dst":19,"cost":35.0,"toll":false},{"src":32,"dst":31,"cost":35.0,"toll":false},{"src":32,"dst":33,"cost":21.959587017352067,"toll":false},{"src":32,"dst":36,"cost":30.96510310509774,"toll":false},{"src":32,"dst":83,"cost":35.0,"toll":false},{"src":32,"dst":90,"cost":9.16715057924308,"toll":true},{"src":33,"dst":6,"cost":35.0,"toll":false},{"src":33,"dst":30,"cost":14.749311938227134,"toll":false},{"src":33,"dst":32,"cost":21.959587017352067,"toll":false},{"src":33,"dst":34,"cost":33.89291051244274,"toll":false},{"src":33,"dst":83,"cost":32.02223601495214,"toll":false},{"src":34,"dst":6,"cost":32.888304871476905,"toll":false},{"src":34,"dst":27,"cost":30.039700946531426,"toll":false},{"src":34,"dst":29,"cost":35.0,"toll":false},{"src":34,"dst":30,"cost":32.29383331673259,"toll":false},{"src":34,"dst":33,"cost":33.89291051244274,"toll":false},{"src":34,"dst":35,"cost":23.767161671155883,"toll":false},{"src":35,"dst":6,"cost":34.609321679610645,"toll":false},{"src":35,"dst":7,"cost":28.258143617324027,"toll":false},{"src":35,"dst":25,"cost":23.38633693485915,"toll":false},{"src":35,"dst":27,"cost":14.085476690181842,"toll":false},{"src":35,"dst":34,"cost":23.767161671155883,"toll":false},{"src":35,"dst":43,"cost":25.616627312437874,"toll":false},{"src":36,"dst":7,"cost":23.917541920932145,"toll":false},{"src":36,"dst":18,"cost":8.736878791247403,"toll":false},{"src":36,"dst":32,"cost":30.96510310509774,"toll":false},{"src":36,"dst":37,"cost":8.736207026102056,"toll":false},{"src":36,"dst":39,"cost":32.07314646450335,"toll":false},{"src":36,"dst":43,"cost":6.39561606449979,"toll":true},{"src":37,"dst":36,"cost":8.736207026102056,"toll":false},{"src":37,"dst":38,"cost":35.0,"toll":false},{"src":37,"dst":39,"cost":14.383293158434846,"toll":false},{"src":37,"dst":41,"cost":32.147373255624146,"toll":false},{"src":37,"dst":43,"cost":28.90464238467788,"toll":false},{"src":38,"dst":19,"cost":22.88810981059121,"toll":false},{"src":38,"dst":31,"cost":35.0,"toll":false},{"src":38,"dst":37,"cost":35.0,"toll":false},{"src":38,"dst":39,"cost":32.28429288915893,"toll":false},{"src":38,"dst":41,"cost":26.350017394409477,"toll":false},{"src":38,"dst":81,"cost":5.7022689072971025,"toll":false},{"src":38,"dst":82,"cost":14.102910247408985,"toll":true},{"src":39,"dst":18,"cost":25.62298101753235,"toll":false},{"src":39,"dst":31,"cost":6.261212384924658,"toll":false},{"src":39,"dst":36,"cost":32.07314646450335,"toll":false},{"src":39,"dst":37,"cost":14.383293158434846,"toll":false},{"src":39,"dst":38,"cost":32.28429288915893,"toll":false},{"src":40,"dst":17,"cost":27.248695041643977,"toll":false},{"src":40,"dst":41,"cost":35.0,"toll":false},{"src":40,"dst":55,"cost":35.0,"toll":false},{"src":40,"dst":56,"cost":17.5,"toll":true},{"src":40,"dst":81,"cost":10.398871435864287,"toll":false},{"src":41,"dst":5,"cost":26.255929701754496,"toll":false},{"src":41,"dst":37,"cost":32.147373255624146,"toll":false},{"src":41,"dst":38,"cost":26.350017394409477,"toll":false},{"src":41,"dst":40,"cost":35.0,"toll":false},{"src":41,"dst":42,"cost":14.401882268512065,"toll":false},{"src":41,"dst":43,"cost":23.6670100533736,"toll":false},{"src":41,"dst":54,"cost":7.290625139638483,"toll":true},{"src":41,"dst":55,"cost":31.492558342809982,"toll":false},{"src":41,"dst":81,"cost":7.826112036986463,"toll":true},{"src":42,"dst":3,"cost":29.04659851130385,"toll":false},{"src":42,"dst":5,"cost":6.632936398629157,"toll":false},{"src":42,"dst":41,"cost":14.401882268512065,"toll":false},{"src":42,"dst":50,"cost":35.0,"toll":false},{"src":42,"dst":54,"cost":27.70374629987859,"toll":false},{"src":43,"dst":5,"cost":22.88060619247216,"toll":false},{"src":43,"dst":7,"cost":17.5,"toll":true},{"src":43,"dst":25,"cost":26.524750265624778,"toll":false},{"src":43,"dst":35,"cost":25.616627312437874,"toll":false},{"src":43,"dst":36,"cost":6.39561606449979,"toll":true},{"src":43,"dst":37,"cost":28.90464238467788,"toll":false},{"src":43,"dst":41,"cost":23.6670100533736,"toll":false},{"src":43,"dst":44,"cost":15.491501674740762,"toll":false},{"src":44,"dst":5,"cost":21.340626323174,"toll":false},{"src":44,"dst":25,"cost":25.610963019187672,"toll":false},{"src":44,"dst":43,"cost":15.491501674740762,"toll":false},{"src":44,"dst":45,"cost":18.96231529067419,"toll":false},{"src":44,"dst":46,"cost":5.084317454687532,"toll":false},{"src":45,"dst":25,"cost":18.455277092911057,"toll":false},{"src":45,"dst":26,"cost":35.0,"toll":false},{"src":45,"dst":44,"cost":18.96231529067419,"toll":false},{"src":45,"dst":46,"cost":27.69600701287228,"toll":false},{"src":46,"dst":3,"cost":28.699372029704282,"toll":false},{"src":46,"dst":5,"cost":26.00701457513923,"toll":false},{"src":46,"dst":26,"cost":17.097977369783646,"toll":false},{"src":46,"dst":44,"cost":5.084317454687532,"toll":false},{"src":46,"dst":45,"cost":27.69600701287228,"toll":false},{"src":46,"dst":47,"cost":31.695243955442304,"toll":false},{"src":47,"dst":3,"cost":9.903373070793208,"toll":true},{"src":47,"dst":4,"cost":12.787859295521681,"toll":true},{"src":47,"dst":10,"cost":7.536911110051758,"toll":false},{"src":47,"dst":24,"cost":6.852669942383832,"toll":true},{"src":47,"dst":26,"cost":19.151819543392744,"toll":false},{"src":47,"dst":46,"cost":31.695243955442304,"toll":false},{"src":48,"dst":3,"cost":7.576173403689467,"toll":false},{"src":48,"dst":4,"cost":35.0,"toll":false},{"src":48,"dst":9,"cost":23.298744235960914,"toll":false},{"src":48,"dst":49,"cost":6.297080660264159,"toll":true},{"src":48,"dst":50,"cost":9.813056237891843,"toll":false},{"src":49,"dst":4,"cost":10.257452266926434,"toll":false},{"src":49,"dst":9,"cost":33.14125491311384,"toll":false},{"src":49,"dst":10,"cost":20.916918223558433,"toll":false},{"src":49,"dst":48,"cost":6.297080660264159,"toll":true},{"src":50,"dst":3,"cost":10.26216828740564,"toll":false},{"src":50,"dst":8,"cost":29.150978712283905,"toll":false},{"src":50,"dst":9,"cost":35.0,"toll":false},{"src":50,"dst":42,"cost":35.0,"toll":false},{"src":50,"dst":48,"cost":9.813056237891843,"toll":false},{"src":50,"dst":53,"cost":7.9552639343559495,"toll":true},{"src":50,"dst":54,"cost":6.330492565121935,"toll":true},{"src":51,"dst":52,"cost":23.997680816053403,"toll":false},{"src":51,"dst":55,"cost":10.45521735255041,"toll":false},{"src":51,"dst":56,"cost":19.204610943730213,"toll":false},{"src":51,"dst":61,"cost":22.435910033122678,"toll":false},{"src":51,"dst":62,"cost":28.95488010902735,"toll":false},{"src":52,"dst":51,"cost":23.997680816053403,"toll":false},{"src":52,"dst":61,"cost":27.279333767071414,"toll":false},{"src":52,"dst":62,"cost":4.156929672368721,"toll":true},{"src":53,"dst":8,"cost":34.950903653677244,"toll":false},{"src":53,"dst":9,"cost":35.0,"toll":false},{"src":53,"dst":50,"cost":7.9552639343559495,"toll":true},{"src":53,"dst":62,"cost":24.10939936070241,"toll":false},{"src":54,"dst":8,"cost":17.66218958147799,"toll":false},{"src":54,"dst":41,"cost":7.290625139638483,"toll":true},{"src":54,"dst":42,"cost":27.70374629987859,"toll":false},{"src":54,"dst":50,"cost":6.330492565121935,"toll":true},{"src":54,"dst":55,"cost":14.9155785889675,"toll":true},{"src":55,"dst":8,"cost":34.17976555468401,"toll":false},{"src":55,"dst":40,"cost":35.0,"toll":false},{"src":55,"dst":41,"cost":31.492558342809982,"toll":false},{"src":55,"dst":51,"cost":10.45521735255041,"toll":false},{"src":55,"dst":54,"cost":14.9155785889675,"toll":true},{"src":55,"dst":56,"cost":28.810354506680024,"toll":false},{"src":55,"dst":62,"cost":5.73880188671099,"toll":true},{"src":56,"dst":11,"cost":8.339171194745601,"toll":false},{"src":56,"dst":17,"cost":27.168879045790447,"toll":false},{"src":56,"dst":40,"cost":17.5,"toll":true},{"src":56,"dst":51,"cost":19.204610943730213,"toll":false},{"src":56,"dst":55,"cost":28.810354506680024,"toll":false},{"src":56,"dst":57,"cost":21.334440482297598,"toll":false},{"src":56,"dst":61,"cost":35.0,"toll":false},{"src":56,"dst":89,"cost":35.0,"toll":false},{"src":57,"dst":11,"cost":23.67420589544997,"toll":false},{"src":57,"dst":56,"cost":21.334440482297598,"toll":false},{"src":57,"dst":58,"cost":10.891170844003401,"toll":false},{"src":57,"dst":60,"cost":3.1026198367730284,"toll":true},{"src":57,"dst":61,"cost":35.0,"toll":false},{"src":58,"dst":11,"cost":13.92653318101821,"toll":false},{"src":58,"dst":57,"cost":10.891170844003401,"toll":false},{"src":58,"dst":59,"cost":35.0,"toll":false},{"src":58,"dst":60,"cost":21.93663752943687,"toll":false},{"src":59,"dst":11,"cost":10.592783165038856,"toll":false},{"src":59,"dst":13,"cost":12.355113618068966,"toll":true},{"src":59,"dst":58,"cost":35.0,"toll":false},{"src":59,"dst":60,"cost":5.426610618132228,"toll":true},{"src":59,"dst":69,"cost":33.28247757440663,"toll":false},{"src":60,"dst":57,"cost":3.1026198367730284,"toll":true},{"src":60,"dst":58,"cost":21.93663752943687,"toll":false},{"src":60,"dst":59,"cost":5.426610618132228,"toll":true},{"src":60,"dst":61,"cost":9.462475541908093,"toll":false},{"src":60,"dst":69,"cost":35.0,"toll":false},{"src":61,"dst":51,"cost":22.435910033122678,"toll":false},{"src":61,"dst":52,"cost":27.279333767071414,"toll":false},{"src":61,"dst":56,"cost":35.0,"toll":false},{"src":61,"dst":57,"cost":35.0,"toll":false},{"src":61,"dst":60,"cost":9.462475541908093,"toll":false},{"src":62,"dst":8,"cost":25.63524408454809,"toll":false},{"src":62,"dst":51,"cost":28.95488010902735,"toll":false},{"src":62,"dst":52,"cost":4.156929672368721,"toll":true},{"src":62,"dst":53,"cost":24.10939936070241,"toll":false},{"src":62,"dst":55,"cost":5.73880188671099,"toll":true},{"src":63,"dst":12,"cost":17.5,"toll":true},{"src":63,"dst":65,"cost":14.76546884306726,"toll":true},{"src":63,"dst":66,"cost":24.171459520006668,"toll":false},{"src":63,"dst":68,"cost":12.23907668361884,"toll":true},{"src":63,"dst":69,"cost":14.681525594499949,"toll":true},{"src":63,"dst":72,"cost":9.470706810968352,"toll":false},{"src":64,"dst":20,"cost":24.677027371758307,"toll":false},{"src":64,"dst":65,"cost":35.0,"toll":false},{"src":64,"dst":66,"cost":33.07923160958208,"toll":false},{"src":64,"dst":67,"cost":24.47541828369881,"toll":false},{"src":65,"dst":63,"cost":14.76546884306726,"toll":true},{"src":65,"dst":64,"cost":35.0,"toll":false},{"src":65,"dst":66,"cost":12.975662540114005,"toll":false},{"src":66,"dst":12,"cost":20.64206348466726,"toll":false},{"src":66,"dst":63,"cost":24.171459520006668,"toll":false},{"src":66,"dst":64,"cost":33.07923160958208,"toll":false},{"src":66,"dst":65,"cost":12.975662540114005,"toll":false},{"src":66,"dst":67,"cost":19.464719021799013,"toll":false},{"src":67,"dst":12,"cost":10.473561851245949,"toll":false},{"src":67,"dst":14,"cost":11.625878279116964,"toll":false},{"src":67,"dst":20,"cost":24.284829505478324,"toll":false},{"src":67,"dst":64,"cost":24.47541828369881,"toll":false},{"src":67,"dst":66,"cost":19.464719021799013,"toll":false},{"src":67,"dst":71,"cost":35.0,"toll":false},{"src":67,"dst":72,"cost":35.0,"toll":false},{"src":68,"dst":13,"cost":4.633325728262582,"toll":true},{"src":68,"dst":63,"cost":12.23907668361884,"toll":true},{"src":68,"dst":69,"cost":9.561397735913255,"toll":false},{"src":68,"dst":70,"cost":26.657673519785142,"toll":false},{"src":68,"dst":72,"cost":19.21530055907917,"toll":false},{"src":69,"dst":13,"cost":5.251873009631446,"toll":true},{"src":69,"dst":59,"cost":33.28247757440663,"toll":false},{"src":69,"dst":60,"cost":35.0,"toll":false},{"src":69,"dst":63,"cost":14.681525594499949,"toll":true},{"src":69,"dst":68,"cost":9.561397735913255,"toll":false},{"src":70,"dst":13,"cost":34.939550234423976,"toll":false},{"src":70,"dst":68,"cost":26.657673519785142,"toll":false},{"src":70,"dst":71,"cost":10.206270355907957,"toll":false},{"src":70,"dst":72,"cost":8.887816771720534,"toll":true},{"src":70,"dst":78,"cost":35.0,"toll":false},{"src":70,"dst":79,"cost":33.803223849464054,"toll":false},{"src":70,"dst":80,"cost":28.63099265173591,"toll":false},{"src":71,"dst":14,"cost":35.0,"toll":false},{"src":71,"dst":67,"cost":35.0,"toll":false},{"src":71,"dst":70,"cost":10.206270355907957,"toll":false},{"src":71,"dst":72,"cost":22.954688470021573,"toll":false},{"src":71,"dst":73,"cost":28.29144246776938,"toll":false},{"src":71,"dst":79,"cost":12.270013635059417,"toll":false},{"src":72,"dst":12,"cost":23.341058763214626,"toll":false},{"src":72,"dst":63,"cost":9.470706810968352,"toll":false},{"src":72,"dst":67,"cost":35.0,"toll":false},{"src":72,"dst":68,"cost":19.21530055907917,"toll":false},{"src":72,"dst":70,"cost":8.887816771720534,"toll":true},{"src":72,"dst":71,"cost":22.954688470021573,"toll":false},{"src":73,"dst":14,"cost":18.62612772518185,"toll":false},{"src":73,"dst":15,"cost":29.688421543116917,"toll":false},{"src":73,"dst":16,"cost":11.482153410570735,"toll":false},{"src":73,"dst":71,"cost":28.29144246776938,"toll":false},{"src":73,"dst":79,"cost":35.0,"toll":false},{"src":74,"dst":1,"cost":9.691156828602299,"toll":true},{"src":74,"dst":16,"cost":33.42320001685904,"toll":false},{"src":74,"dst":21,"cost":20.385068847385323,"toll":false},{"src":74,"dst":76,"cost":17.051572225886893,"toll":true},{"src":74,"dst":77,"cost":5.9212996729858425,"toll":true},{"src":74,"dst":78,"cost":3.538401557544751,"toll":true},{"src":74,"dst":79,"cost":12.963421910586906,"toll":false},{"src":75,"dst":16,"cost":2.557757402889405,"toll":true},{"src":75,"dst":20,"cost":35.0,"toll":false},{"src":75,"dst":77,"cost":17.5,"toll":true},{"src":75,"dst":97,"cost":20.602671402022295,"toll":false},{"src":75,"dst":98,"cost":20.063478348648673,"toll":false},{"src":76,"dst":1,"cost":20.234432281315712,"toll":false},{"src":76,"dst":74,"cost":17.051572225886893,"toll":true},{"src":76,"dst":78,"cost":17.28762766552261,"toll":false},{"src":76,"dst":85,"cost":35.0,"toll":false},{"src":76,"dst":86,"cost":7.941953753310495,"toll":false},{"src":76,"dst":87,"cost":14.871111673642805,"toll":false},{"src":76,"dst":88,"cost":25.626004372360885,"toll":false},{"src":76,"dst":95,"cost":10.339687327441643,"toll":false},{"src":77,"dst":16,"cost":5.209917287303246,"toll":true},{"src":77,"dst":21,"cost":28.053694293617223,"toll":false},{"src":77,"dst":74,"cost":5.9212996729858425,"toll":true},{"src":77,"dst":75,"cost":17.5,"toll":true},{"src":77,"dst":97,"cost":21.60009720279686,"toll":false},{"src":78,"dst":70,"cost":35.0,"toll":false},{"src":78,"dst":74,"cost":3.538401557544751,"toll":true},{"src":78,"dst":76,"cost":17.28762766552261,"toll":false},{"src":78,"dst":79,"cost":12.318162937273058,"toll":false},{"src":78,"dst":80,"cost":7.113152308439903,"toll":true},{"src":78,"dst":88,"cost":22.780921059418702,"toll":false},{"src":79,"dst":16,"cost":19.333252965211408,"toll":false},{"src":79,"dst":70,"cost":33.803223849464054,"toll":false},{"src":79,"dst":71,"cost":12.270013635059417,"toll":false},{"src":79,"dst":73,"cost":35.0,"toll":false},{"src":79,"dst":74,"cost":12.963421910586906,"toll":false},{"src":79,"dst":78,"cost":12.318162937273058,"toll":false},{"src":80,"dst":11,"cost":33.2113158010213,"toll":false},{"src":80,"dst":13,"cost":3.8669285466641714,"toll":true},{"src":80,"dst":70,"cost":28.63099265173591,"toll":false},{"src":80,"dst":78,"cost":7.113152308439903,"toll":true},{"src":80,"dst":84,"cost":4.7227063717081705,"toll":true},{"src":80,"dst":88,"cost":9.367783963340166,"toll":false},{"src":80,"dst":89,"cost":17.5,"toll":true},{"src":81,"dst":17,"cost":22.57035180236781,"toll":false},{"src":81,"dst":38,"cost":5.7022689072971025,"toll":false},{"src":81,"dst":40,"cost":10.398871435864287,"toll":false},{"src":81,"dst":41,"cost":7.826112036986463,"toll":true},{"src":81,"dst":82,"cost":4.662264938857032,"toll":true},{"src":81,"dst":84,"cost":35.0,"toll":false},{"src":81,"dst":89,"cost":6.159373375841145,"toll":true},{"src":82,"dst":19,"cost":6.471042753087826,"toll":true},{"src":82,"dst":38,"cost":14.102910247408985,"toll":true},{"src":82,"dst":81,"cost":4.662264938857032,"toll":true},{"src":82,"dst":84,"cost":9.109071349444557,"toll":true},{"src":83,"dst":30,"cost":8.471127521034486,"toll":false},{"src":83,"dst":32,"cost":35.0,"toll":false},{"src":83,"dst":33,"cost":32.02223601495214,"toll":false},{"src":83,"dst":90,"cost":35.0,"toll":false},{"src":83,"dst":91,"cost":10.765578657279807,"toll":false},{"src":83,"dst":93,"cost":17.431026248076204,"toll":true},{"src":84,"dst":19,"cost":33.92886600921691,"toll":false},{"src":84,"dst":80,"cost":4.7227063717081705,"toll":true},{"src":84,"dst":81,"cost":35.0,"toll":false},{"src":84,"dst":82,"cost":9.109071349444557,"toll":true},{"src":84,"dst":85,"cost":32.26763906646066,"toll":false},{"src":84,"dst":88,"cost":20.10905726174186,"toll":false},{"src":84,"dst":89,"cost":35.0,"toll":false},{"src":85,"dst":19,"cost":12.06161084561668,"toll":false},{"src":85,"dst":76,"cost":35.0,"toll":false},{"src":85,"dst":84,"cost":32.26763906646066,"toll":false},{"src":85,"dst":87,"cost":14.020254719309547,"toll":false},{"src":85,"dst":88,"cost":16.819327914050206,"toll":false},{"src":85,"dst":90,"cost":2.5525600904676193,"toll":true},{"src":86,"dst":76,"cost":7.941953753310495,"toll":false},{"src":86,"dst":87,"cost":11.42937042336976,"toll":false},{"src":86,"dst":90,"cost":35.0,"toll":false},{"src":86,"dst":92,"cost":29.82326094894488,"toll":false},{"src":86,"dst":95,"cost":20.914299108488898,"toll":false},{"src":87,"dst":76,"cost":14.871111673642805,"toll":false},{"src":87,"dst":85,"cost":14.020254719309547,"toll":false},{"src":87,"dst":86,"cost":11.42937042336976,"toll":false},{"src":87,"dst":90,"cost":35.0,"toll":false},{"src":88,"dst":76,"cost":25.626004372360885,"toll":false},{"src":88,"dst":78,"cost":22.780921059418702,"toll":false},{"src":88,"dst":80,"cost":9.367783963340166,"toll":false},{"src":88,"dst":84,"cost":20.10905726174186,"toll":false},{"src":88,"dst":85,"cost":16.819327914050206,"toll":false},{"src":89,"dst":11,"cost":3.384094479168793,"toll":true},{"src":89,"dst":17,"cost":35.0,"toll":false},{"src":89,"dst":56,"cost":35.0,"toll":false},{"src":89,"dst":80,"cost":17.5,"toll":true},{"src":89,"dst":81,"cost":6.159373375841145,"toll":true},{"src":89,"dst":84,"cost":35.0,"toll":false},{"src":90,"dst":19,"cost":19.401306478002173,"toll":false},{"src":90,"dst":32,"cost":9.16715057924308,"toll":true},{"src":90,"dst":83,"cost":35.0,"toll":false},{"src":90,"dst":85,"cost":2.5525600904676193,"toll":true},{"src":90,"dst":86,"cost":35.0,"toll":false},{"src":90,"dst":87,"cost":35.0,"toll":false},{"src":90,"dst":91,"cost":35.0,"toll":false},{"src":90,"dst":92,"cost":16.8217486575306,"toll":false},{"src":91,"dst":83,"cost":10.765578657279807,"toll":false},{"src":91,"dst":90,"cost":35.0,"toll":false},{"src":91,"dst":92,"cost":35.0,"toll":false},{"src":91,"dst":93,"cost":18.79128489970489,"toll":false},{"src":91,"dst":94,"cost":18.634147600994012,"toll":false},{"src":92,"dst":86,"cost":29.82326094894488,"toll":false},{"src":92,"dst":90,"cost":16.8217486575306,"toll":false},{"src":92,"dst":91,"cost":35.0,"toll":false},{"src":92,"dst":94,"cost":35.0,"toll":false},{"src":92,"dst":95,"cost":19.65674820620173,"toll":false},{"src":93,"dst":1,"cost":4.06157731046561,"toll":true},{"src":93,"dst":2,"cost":25.37356788492537,"toll":false},{"src":93,"dst":29,"cost":6.342880324826749,"toll":true},{"src":93,"dst":30,"cost":19.50758331929983,"toll":false},{"src":93,"dst":83,"cost":17.431026248076204,"toll":true},{"src":93,"dst":91,"cost":18.79128489970489,"toll":false},{"src":93,"dst":94,"cost":20.758535828088753,"toll":false},{"src":93,"dst":100,"cost":26.95467146105658,"toll":false},{"src":94,"dst":1,"cost":19.530658177194063,"toll":false},{"src":94,"dst":91,"cost":18.634147600994012,"toll":false},{"src":94,"dst":92,"cost":35.0,"toll":false},{"src":94,"dst":93,"cost":20.758535828088753,"toll":false},{"src":94,"dst":95,"cost":11.199315529156717,"toll":false},{"src":95,"dst":1,"cost":19.530273645812834,"toll":false},{"src":95,"dst":76,"cost":10.339687327441643,"toll":false},{"src":95,"dst":86,"cost":20.914299108488898,"toll":false},{"src":95,"dst":92,"cost":19.65674820620173,"toll":false},{"src":95,"dst":94,"cost":11.199315529156717,"toll":false},{"src":96,"dst":1,"cost":35.0,"toll":false},{"src":96,"dst":2,"cost":30.04448510622299,"toll":false},{"src":96,"dst":21,"cost":6.820495698080055,"toll":false},{"src":96,"dst":97,"cost":35.0,"toll":false},{"src":97,"dst":2,"cost":28.739338967430996,"toll":false},{"src":97,"dst":21,"cost":9.416427859406491,"toll":false},{"src":97,"dst":75,"cost":20.602671402022295,"toll":false},{"src":97,"dst":77,"cost":21.60009720279686,"toll":false},{"src":97,"dst":96,"cost":35.0,"toll":false},{"src":97,"dst":98,"cost":16.66034959426149,"toll":true},{"src":97,"dst":99,"cost":35.0,"toll":false},{"src":98,"dst":75,"cost":20.063478348648673,"toll":false},{"src":98,"dst":97,"cost":16.66034959426149,"toll":true},{"src":98,"dst":99,"cost":19.43488130444723,"toll":false},{"src":98,"dst":100,"cost":17.71430474409704,"toll":false},{"src":99,"dst":2,"cost":22.697143203431597,"toll":false},{"src":99,"dst":97,"cost":35.0,"toll":false},{"src":99,"dst":98,"cost":19.43488130444723,"toll":false},{"src":99,"dst":100,"cost":12.882068334316147,"toll":false},{"src":100,"dst":2,"cost":31.70588413457027,"toll":false},{"src":100,"dst":29,"cost":8.293140096788402,"toll":true},{"src":100,"dst":93,"cost":26.95467146105658,"toll":false},{"src":100,"dst":98,"cost":17.71430474409704,"toll":false},{"src":100,"dst":99,"cost":12.882068334316147,"toll":false}],"K":[{"orig":24,"dest":10,"demand":82.4411328322077},{"orig":90,"dest":53,"demand":34.22663932206601},{"orig":79,"dest":97,"demand":21.986282564531237},{"orig":66,"dest":43,"demand":9.5355423321631},{"orig":43,"dest":90,"demand":55.28670472217115},{"orig":94,"dest":24,"demand":74.8553121864126},{"orig":47,"dest":99,"demand":82.21505801344},{"orig":49,"dest":6,"demand":53.13157369917203},{"orig":93,"dest":79,"demand":28.602511155122578},{"orig":34,"dest":36,"demand":5.9314478553983765},{"orig":79,"dest":76,"demand":86.67188560558775},{"orig":72,"dest":63,"demand":4.622806228839897},{"orig":69,"dest":18,"demand":8.079526950488571},{"orig":24,"dest":29,"demand":55.14635508782505},{"orig":18,"dest":93,"demand":79.90087349699247},{"orig":11,"dest":63,"demand":17.32280272208472},{"orig":24,"dest":16,"demand":83.2031377392062},{"orig":62,"dest":52,"demand":17.274464066569898},{"orig":21,"dest":69,"demand":33.02102026520598},{"orig":64,"dest":75,"demand":91.95004401638808},{"orig":21,"dest":44,"demand":7.386347497022403},{"orig":47,"dest":2,"demand":48.68181181962051},{"orig":52,"dest":38,"demand":18.066655076999808},{"orig":15,"dest":64,"demand":50.64914009855391},{"orig":92,"dest":42,"demand":56.59593519785997},{"orig":69,"dest":9,"demand":35.49601789415784},{"orig":9,"dest":60,"demand":42.79922879675063},{"orig":88,"dest":44,"demand":76.4989179674453},{"orig":60,"dest":13,"demand":29.044498126034576},{"orig":63,"dest":17,"demand":64.68333332097785},{"orig":35,"dest":36,"demand":44.61042499847838},{"orig":53,"dest":23,"demand":61.760637349369375},{"orig":52,"dest":41,"demand":91.48710136108284},{"orig":79,"dest":58,"demand":42.622278997662896},{"orig":68,"dest":23,"demand":96.1019429207815},{"orig":53,"dest":16,"demand":57.708305076123644},{"orig":15,"dest":57,"demand":59.11387493116364},{"orig":87,"dest":99,"demand":55.65789096972632},{"orig":67,"dest":74,"demand":16.982404988534},{"orig":8,"dest":22,"demand":3.692787628917232},{"orig":2,"dest":57,"demand":92.09094055143326},{"orig":85,"dest":2,"demand":4.224757086548608},{"orig":90,"dest":22,"demand":75.79723523113039},{"orig":44,"dest":26,"demand":65.66224258144204}]}}