{"problem":{"V":64,"A":[{"src":1,"dst":42,"cost":34.503281791052345,"toll":false},{"src":1,"dst":43,"cost":33.80726922707123,"toll":false},{"src":1,"dst":46,"cost":22.797982722197165,"toll":false},{"src":1,"dst":47,"cost":28.05999007286647,"toll":false},{"src":1,"dst":51,"cost":28.276342879962026,"toll":false},{"src":1,"dst":52,"cost":6.290814566052758,"toll":true},{"src":2,"dst":9,"cost":35.0,"toll":false},{"src":2,"dst":10,"cost":35.0,"toll":false},{"src":2,"dst":11,"cost":17.563563451203322,"toll":false},{"src":2,"dst":14,"cost":35.0,"toll":false},{"src":2,"dst":55,"cost":29.24030354816542,"toll":false},{"src":3,"dst":13,"cost":20.55751685138185,"toll":false},{"src":3,"dst":14,"cost":9.971394775199206,"toll":false},{"src":3,"dst":15,"cost":11.153322870136401,"toll":false},{"src":3,"dst":16,"cost":11.60357126521237,"toll":false},{"src":3,"dst":19,"cost":10.986546296362008,"toll":true},{"src":3,"dst":20,"cost":35.0,"toll":false},{"src":4,"dst":19,"cost":10.923877041814233,"toll":false},{"src":4,"dst":22,"cost":28.265051391371752,"toll":false},{"src":4,"dst":24,"cost":35.0,"toll":false},{"src":4,"dst":25,"cost":35.0,"toll":false},{"src":4,"dst":26,"cost":35.0,"toll":false},{"src":4,"dst":27,"cost":33.82916588372995,"toll":false},{"src":4,"dst":28,"cost":3.6029340199401343,"toll":true},{"src":4,"dst":30,"cost":6.199467997196708,"toll":true},{"src":5,"dst":33,"cost":16.075467755173488,"toll":false},{"src":5,"dst":35,"cost":35.0,"toll":false},{"src":5,"dst":36,"cost":14.138747389799448,"toll":false},{"src":5,"dst":37,"cost":7.495908484079636,"toll":true},{"src":6,"dst":8,"cost":7.730353926662704,"toll":true},{"src":6,"dst":41,"cost":26.007474404167098,"toll":false},{"src":6,"dst":42,"cost":35.0,"toll":false},{"src":6,"dst":43,"cost":32.233750142137865,"toll":false},{"src":6,"dst":44,"cost":7.1355244897727035,"toll":true},{"src":6,"dst":62,"cost":26.150705066430895,"toll":false},{"src":7,"dst":8,"cost":26.128886459250204,"toll":false},{"src":7,"dst":12,"cost":26.615024363842064,"toll":false},{"src":7,"dst":53,"cost":5.122293442231898,"toll":true},{"src":7,"dst":58,"cost":6.555151928774793,"toll":false},{"src":7,"dst":61,"cost":6.842933330417852,"toll":true},{"src":7,"dst":64,"cost":35.0,"toll":false},{"src":8,"dst":6,"cost":7.730353926662704,"toll":true},{"src":8,"dst":7,"cost":26.128886459250204,"toll":false},{"src":8,"dst":42,"cost":6.25602546089662,"toll":false},{"src":8,"dst":52,"cost":9.987609465589571,"toll":true},{"src":8,"dst":53,"cost":2.7070418249144375,"toll":true},{"src":8,"dst":62,"cost":12.630415809291016,"toll":false},{"src":8,"dst":64,"cost":13.067249916142302,"toll":true},{"src":9,"dst":2,"cost":35.0,"toll":false},{"src":9,"dst":10,"cost":17.5932779136594,"toll":false},{"src":9,"dst":55,"cost":25.29420339219237,"toll":false},{"src":9,"dst":57,"cost":9.84176837497289,"toll":false},{"src":10,"dst":2,"cost":35.0,"toll":false},{"src":10,"dst":9,"cost":17.5932779136594,"toll":false},{"src":10,"dst":11,"cost":4.5463037035194525,"toll":true},{"src":10,"dst":57,"cost":13.866453798513437,"toll":true},{"src":11,"dst":2,"cost":17.563563451203322,"toll":false},{"src":11,"dst":10,"cost":4.5463037035194525,"toll":true},{"src":11,"dst":57,"cost":31.965148716826096,"toll":false},{"src":11,"dst":59,"cost":19.782470296122543,"toll":false},{"src":12,"dst":7,"cost":26.615024363842064,"toll":false},{"src":12,"dst":59,"cost":16.331911705986023,"toll":false},{"src":12,"dst":60,"cost":35.0,"toll":false},{"src":12,"dst":61,"cost":35.0,"toll":false},{"src":12,"dst":63,"cost":19.337413145852828,"toll":false},{"src":12,"dst":64,"cost":23.836682469765954,"toll":false},{"src":13,"dst":3,"cost":20.55751685138185,"toll":false},{"src":13,"dst":14,"cost":33.83222603190188,"toll":false},{"src":13,"dst":16,"cost":35.0,"toll":false},{"src":13,"dst":17,"cost":35.0,"toll":false},{"src":14,"dst":2,"cost":35.0,"toll":false},{"src":14,"dst":3,"cost":9.971394775199206,"toll":false},{"src":14,"dst":13,"cost":33.83222603190188,"toll":false},{"src":14,"dst":15,"cost":31.774818439347325,"toll":false},{"src":14,"dst":55,"cost":5.5604661390234424,"toll":false},{"src":15,"dst":3,"cost":11.153322870136401,"toll":false},{"src":15,"dst":14,"cost":31.774818439347325,"toll":false},{"src":15,"dst":20,"cost":15.109639286077117,"toll":false},{"src":15,"dst":22,"cost":5.184863422970735,"toll":true},{"src":15,"dst":28,"cost":5.336507730966149,"toll":true},{"src":15,"dst":49,"cost":35.0,"toll":false},{"src":15,"dst":55,"cost":5.244686883364983,"toll":true},{"src":16,"dst":3,"cost":11.60357126521237,"toll":false},{"src":16,"dst":13,"cost":35.0,"toll":false},{"src":16,"dst":17,"cost":18.190928138746457,"toll":false},{"src":16,"dst":19,"cost":24.243021530289987,"toll":false},{"src":17,"dst":13,"cost":35.0,"toll":false},{"src":17,"dst":16,"cost":18.190928138746457,"toll":false},{"src":17,"dst":18,"cost":17.196270256702768,"toll":false},{"src":17,"dst":19,"cost":32.57422432930517,"toll":false},{"src":18,"dst":17,"cost":17.196270256702768,"toll":false},{"src":18,"dst":19,"cost":35.0,"toll":false},{"src":18,"dst":27,"cost":20.096958791486585,"toll":false},{"src":18,"dst":29,"cost":30.83898921701281,"toll":false},{"src":19,"dst":3,"cost":10.986546296362008,"toll":true},{"src":19,"dst":4,"cost":10.923877041814233,"toll":false},{"src":19,"dst":16,"cost":24.243021530289987,"toll":false},{"src":19,"dst":17,"cost":32.57422432930517,"toll":false},{"src":19,"dst":18,"cost":35.0,"toll":false},{"src":19,"dst":20,"cost":18.358321660394015,"toll":false},{"src":19,"dst":27,"cost":14.58589579472837,"toll":false},{"src":19,"dst":28,"cost":24.134462931951475,"toll":false},{"src":20,"dst":3,"cost":35.0,"toll":false},{"src":20,"dst":15,"cost":15.109639286077117,"toll":false},{"src":20,"dst":19,"cost":18.358321660394015,"toll":false},{"src":20,"dst":28,"cost":22.967879048458755,"toll":false},{"src":21,"dst":22,"cost":27.93396840015405,"toll":false},{"src":21,"dst":23,"cost":11.182192726289186,"toll":false},{"src":21,"dst":32,"cost":21.836967244293064,"toll":false},{"src":21,"dst":48,"cost":5.02757359402942,"toll":true},{"src":21,"dst":49,"cost":10.833827298838408,"toll":false},{"src":22,"dst":4,"cost":28.265051391371752,"toll":false},{"src":22,"dst":15,"cost":5.184863422970735,"toll":true},{"src":22,"dst":21,"cost":27.93396840015405,"toll":false},{"src":22,"dst":23,"cost":9.046814339238576,"toll":false},{"src":22,"dst":24,"cost":4.731488788610406,"toll":true},{"src":22,"dst":28,"cost":35.0,"toll":false},{"src":22,"dst":49,"cost":7.250509494625478,"toll":true},{"src":23,"dst":21,"cost":11.182192726289186,"toll":false},{"src":23,"dst":22,"cost":9.046814339238576,"toll":false},{"src":23,"dst":24,"cost":15.665947025008014,"toll":false},{"src":23,"dst":31,"cost":34.25724418981821,"toll":false},{"src":23,"dst":32,"cost":23.843790740518134,"toll":false},{"src":24,"dst":4,"cost":35.0,"toll":false},{"src":24,"dst":22,"cost":4.731488788610406,"toll":true},{"src":24,"dst":23,"cost":15.665947025008014,"toll":false},{"src":24,"dst":30,"cost":12.199082834515488,"toll":true},{"src":24,"dst":31,"cost":21.838367101544215,"toll":false},{"src":25,"dst":4,"cost":35.0,"toll":false},{"src":25,"dst":26,"cost":35.0,"toll":false},{"src":25,"dst":29,"cost":11.627365441446946,"toll":false},{"src":25,"dst":30,"cost":18.749844006305594,"toll":false},{"src":26,"dst":4,"cost":35.0,"toll":false},{"src":26,"dst":25,"cost":35.0,"toll":false},{"src":26,"dst":27,"cost":32.2316421070644,"toll":false},{"src":26,"dst":29,"cost":25.097193544942716,"toll":false},{"src":27,"dst":4,"cost":33.82916588372995,"toll":false},{"src":27,"dst":18,"cost":20.096958791486585,"toll":false},{"src":27,"dst":19,"cost":14.58589579472837,"toll":false},{"src":27,"dst":26,"cost":32.2316421070644,"toll":false},{"src":27,"dst":29,"cost":16.634806447229334,"toll":false},{"src":28,"dst":4,"cost":3.6029340199401343,"toll":true},{"src":28,"dst":15,"cost":5.336507730966149,"toll":true},{"src":28,"dst":19,"cost":24.134462931951475,"toll":false},{"src":28,"dst":20,"cost":22.967879048458755,"toll":false},{"src":28,"dst":22,"cost":35.0,"toll":false},{"src":29,"dst":18,"cost":30.83898921701281,"toll":false},{"src":29,"dst":25,"cost":11.627365441446946,"toll":false},{"src":29,"dst":26,"cost":25.097193544942716,"toll":false},{"src":29,"dst":27,"cost":16.634806447229334,"toll":false},{"src":30,"dst":4,"cost":6.199467997196708,"toll":true},{"src":30,"dst":24,"cost":12.199082834515488,"toll":true},{"src":30,"dst":25,"cost":18.749844006305594,"toll":false},{"src":30,"dst":31,"cost":26.280481450813095,"toll":false},{"src":31,"dst":23,"cost":34.25724418981821,"toll":false},{"src":31,"dst":24,"cost":21.838367101544215,"toll":false},{"src":31,"dst":30,"cost":26.280481450813095,"toll":false},{"src":31,"dst":32,"cost":27.50983465260619,"toll":false},{"src":32,"dst":21,"cost":21.836967244293064,"toll":false},{"src":32,"dst":23,"cost":23.843790740518134,"toll":false},{"src":32,"dst":31,"cost":27.50983465260619,"toll":false},{"src":32,"dst":48,"cost":24.238342824993218,"toll":false},{"src":33,"dst":5,"cost":16.075467755173488,"toll":false},{"src":33,"dst":36,"cost":8.83302388486793,"toll":false},{"src":33,"dst":46,"cost":34.022045929384056,"toll":false},{"src":34,"dst":35,"cost":6.956578709619346,"toll":true},{"src":34,"dst":37,"cost":11.5384994943931,"toll":false},{"src":34,"dst":38,"cost":12.295710923220815,"toll":false},{"src":34,"dst":39,"cost":5.17541488884941,"toll":false},{"src":35,"dst":5,"cost":35.0,"toll":false},{"src":35,"dst":34,"cost":6.956578709619346,"toll":true},{"src":35,"dst":37,"cost":35.0,"toll":false},{"src":35,"dst":38,"cost":6.7124815259157184,"toll":false},{"src":36,"dst":5,"cost":14.138747389799448,"toll":false},{"src":36,"dst":33,"cost":8.83302388486793,"toll":false},{"src":36,"dst":37,"cost":35.0,"toll":false},{"src":36,"dst":45,"cost":29.906643103819455,"toll":false},{"src":36,"dst":46,"cost":35.0,"toll":false},{"src":37,"dst":5,"cost":7.495908484079636,"toll":true},{"src":37,"dst":34,"cost":11.5384994943931,"toll":false},{"src":37,"dst":35,"cost":35.0,"toll":false},{"src":37,"dst":36,"cost":35.0,"toll":false},{"src":37,"dst":39,"cost":27.833254745601252,"toll":false},{"src":37,"dst":45,"cost":3.1946664291258293,"toll":true},{"src":38,"dst":34,"cost":12.295710923220815,"toll":false},{"src":38,"dst":35,"cost":6.7124815259157184,"toll":false},{"src":38,"dst":39,"cost":5.741555943345222,"toll":true},{"src":38,"dst":41,"cost":19.88413051481114,"toll":false},{"src":39,"dst":34,"cost":5.17541488884941,"toll":false},{"src":39,"dst":37,"cost":27.833254745601252,"toll":false},{"src":39,"dst":38,"cost":5.741555943345222,"toll":true},{"src":39,"dst":40,"cost":14.136891034279573,"toll":false},{"src":39,"dst":41,"cost":15.407568663421122,"toll":true},{"src":39,"dst":45,"cost":35.0,"toll":false},{"src":40,"dst":39,"cost":14.136891034279573,"toll":false},{"src":40,"dst":41,"cost":33.95263702925641,"toll":false},{"src":40,"dst":44,"cost":13.58213880783951,"toll":false},{"src":40,"dst":45,"cost":13.130491876482544,"toll":false},{"src":41,"dst":6,"cost":26.007474404167098,"toll":false},{"src":41,"dst":38,"cost":19.88413051481114,"toll":false},{"src":41,"dst":39,"cost":15.407568663421122,"toll":true},{"src":41,"dst":40,"cost":33.95263702925641,"toll":false},{"src":41,"dst":44,"cost":25.900881828766305,"toll":false},{"src":42,"dst":1,"cost":34.503281791052345,"toll":false},{"src":42,"dst":6,"cost":35.0,"toll":false},{"src":42,"dst":8,"cost":6.25602546089662,"toll":false},{"src":42,"dst":43,"cost":26.4802364390973,"toll":false},{"src":42,"dst":52,"cost":35.0,"toll":false},{"src":43,"dst":1,"cost":33.80726922707123,"toll":false},{"src":43,"dst":6,"cost":32.233750142137865,"toll":false},{"src":43,"dst":42,"cost":26.4802364390973,"toll":false},{"src":43,"dst":44,"cost":29.944395504622634,"toll":false},{"src":43,"dst":45,"cost":35.0,"toll":false},{"src":43,"dst":46,"cost":27.48218710497152,"toll":false},{"src":44,"dst":6,"cost":7.1355244897727035,"toll":true},{"src":44,"dst":40,"cost":13.58213880783951,"toll":false},{"src":44,"dst":41,"cost":25.900881828766305,"toll":false},{"src":44,"dst":43,"cost":29.944395504622634,"toll":false},{"src":44,"dst":45,"cost":5.781940469489564,"toll":true},{"src":45,"dst":36,"cost":29.906643103819455,"toll":false},{"src":45,"dst":37,"cost":3.1946664291258293,"toll":true},{"src":45,"dst":39,"cost":35.0,"toll":false},{"src":45,"dst":40,"cost":13.130491876482544,"toll":false},{"src":45,"dst":43,"cost":35.0,"toll":false},{"src":45,"dst":44,"cost":5.781940469489564,"toll":true},{"src":45,"dst":46,"cost":30.31283151295852,"toll":false},{"src":46,"dst":1,"cost":22.797982722197165,"toll":false},{"src":46,"dst":33,"cost":34.022045929384056,"toll":false},{"src":46,"dst":36,"cost":35.0,"toll":false},{"src":46,"dst":43,"cost":27.48218710497152,"toll":false},{"src":46,"dst":45,"cost":30.31283151295852,"toll":false},{"src":46,"dst":47,"cost":20.559328996469894,"toll":false},{"src":47,"dst":1,"cost":28.05999007286647,"toll":false},{"src":47,"dst":46,"cost":20.559328996469894,"toll":false},{"src":47,"dst":50,"cost":35.0,"toll":false},{"src":47,"dst":51,"cost":35.0,"toll":false},{"src":48,"dst":21,"cost":5.02757359402942,"toll":true},{"src":48,"dst":32,"cost":24.238342824993218,"toll":false},{"src":48,"dst":49,"cost":23.821209805422278,"toll":false},{"src":48,"dst":50,"cost":35.0,"toll":false},{"src":49,"dst":15,"cost":35.0,"toll":false},{"src":49,"dst":21,"cost":10.833827298838408,"toll":false},{"src":49,"dst":22,"cost":7.250509494625478,"toll":true},{"src":49,"dst":48,"cost":23.821209805422278,"toll":false},{"src":49,"dst":50,"cost":35.0,"toll":false},{"src":49,"dst":51,"cost":35.0,"toll":false},{"src":49,"dst":52,"cost":12.201703571633622,"toll":true},{"src":49,"dst":56,"cost":30.37613401686286,"toll":false},{"src":50,"dst":47,"cost":35.0,"toll":false},{"src":50,"dst":48,"cost":35.0,"toll":false},{"src":50,"dst":49,"cost":35.0,"toll":false},{"src":50,"dst":51,"cost":35.0,"toll":false},{"src":51,"dst":1,"cost":28.276342879962026,"toll":false},{"src":51,"dst":47,"cost":35.0,"toll":false},{"src":51,"dst":49,"cost":35.0,"toll":false},{"src":51,"dst":50,"cost":35.0,"toll":false},{"src":51,"dst":52,"cost":25.892085006536306,"toll":false},{"src":52,"dst":1,"cost":6.290814566052758,"toll":true},{"src":52,"dst":8,"cost":9.987609465589571,"toll":true},{"src":52,"dst":42,"cost":35.0,"toll":false},{"src":52,"dst":49,"cost":12.201703571633622,"toll":true},{"src":52,"dst":51,"cost":25.892085006536306,"toll":false},{"src":52,"dst":53,"cost":28.534505921222124,"toll":false},{"src":52,"dst":56,"cost":35.0,"toll":false},{"src":53,"dst":7,"cost":5.122293442231898,"toll":true},{"src":53,"dst":8,"cost":2.7070418249144375,"toll":true},{"src":53,"dst":52,"cost":28.534505921222124,"toll":false},{"src":53,"dst":54,"cost":35.0,"toll":false},{"src":53,"dst":56,"cost":32.90275549951549,"toll":false},{"src":53,"dst":58,"cost":6.855154602926058,"toll":true},{"src":54,"dst":53,"cost":35.0,"toll":false},{"src":54,"dst":56,"cost":25.81228158237608,"toll":false},{"src":54,"dst":58,"cost":6.501408714442798,"toll":false},{"src":54,"dst":61,"cost":35.0,"toll":false},{"src":55,"dst":2,"cost":29.24030354816542,"toll":false},{"src":55,"dst":9,"cost":25.29420339219237,"toll":false},{"src":55,"dst":14,"cost":5.5604661390234424,"toll":false},{"src":55,"dst":15,"cost":5.244686883364983,"toll":true},{"src":55,"dst":56,"cost":35.0,"toll":false},{"src":55,"dst":57,"cost":10.47976754874213,"toll":true},{"src":55,"dst":61,"cost":17.5,"toll":true},{"src":56,"dst":49,"cost":30.37613401686286,"toll":false},{"src":56,"dst":52,"cost":35.0,"toll":false},{"src":56,"dst":53,"cost":32.90275549951549,"toll":false},{"src":56,"dst":54,"cost":25.81228158237608,"toll":false},{"src":56,"dst":55,"cost":35.0,"toll":false},{"src":56,"dst":61,"cost":35.0,"toll":false},{"src":57,"dst":9,"cost":9.84176837497289,"toll":false},{"src":57,"dst":10,"cost":13.866453798513437,"toll":true},{"src":57,"dst":11,"cost":31.965148716826096,"toll":false},{"src":57,"dst":55,"cost":10.47976754874213,"toll":true},{"src":57,"dst":59,"cost":17.5,"toll":true},{"src":57,"dst":60,"cost":20.007293941905196,"toll":false},{"src":57,"dst":61,"cost":24.23141520952149,"toll":false},{"src":58,"dst":7,"cost":6.555151928774793,"toll":false},{"src":58,"dst":53,"cost":6.855154602926058,"toll":true},{"src":58,"dst":54,"cost":6.501408714442798,"toll":false},{"src":58,"dst":61,"cost":10.596674520583978,"toll":false},{"src":59,"dst":11,"cost":19.782470296122543,"toll":false},{"src":59,"dst":12,"cost":16.331911705986023,"toll":false},{"src":59,"dst":57,"cost":17.5,"toll":true},{"src":59,"dst":60,"cost":35.0,"toll":false},{"src":59,"dst":63,"cost":3.3956475434355555,"toll":true},{"src":60,"dst":12,"cost":35.0,"toll":false},{"src":60,"dst":57,"cost":20.007293941905196,"toll":false},{"src":60,"dst":59,"cost":35.0,"toll":false},{"src":60,"dst":61,"cost":23.004925978213777,"toll":false},{"src":61,"dst":7,"cost":6.842933330417852,"toll":true},{"src":61,"dst":12,"cost":35.0,"toll":false},{"src":61,"dst":54,"cost":35.0,"toll":false},{"src":61,"dst":55,"cost":17.5,"toll":true},{"src":61,"dst":56,"cost":35.0,"toll":false},{"src":61,"dst":57,"cost":24.23141520952149,"toll":false},{"src":61,"dst":58,"cost":10.596674520583978,"toll":false},{"src":61,"dst":60,"cost":23.004925978213777,"toll":false},{"src":62,"dst":6,"cost":26.150705066430895,"toll":false},{"src":62,"dst":8,"cost":12.630415809291016,"toll":false},{"src":62,"dst":63,"cost":17.5,"toll":true},{"src":62,"dst":64,"cost":21.968757095503978,"toll":false},{"src":63,"dst":12,"cost":19.337413145852828,"toll":false},{"src":63,"dst":59,"cost":3.3956475434355555,"toll":true},{"src":63,"dst":62,"cost":17.5,"toll":true},{"src":63,"dst":64,"cost":16.80684912531906,"toll":false},{"src":64,"dst":7,"cost":35.0,"toll":false},{"src":64,"dst":8,"cost":13.067249916142302,"toll":true},{"src":64,"dst":12,"cost":23.836682469765954,"toll":false},{"src":64,"dst":62,"cost":21.968757095503978,"toll":false},{"src":64,"dst":63,"cost":16.80684912531906,"toll":false}],"K":[{"orig":64,"dest":6,"demand":67.82103850654764},{"orig":4,"dest":34,"demand":72.15682479856018},{"orig":22,"dest":30,"demand":13.630669222568304},{"orig":52,"dest":11,"demand":87.59008709425292},{"orig":47,"dest":42,"demand":76.11217142992346},{"orig":58,"dest":29,"demand":84.58276804136985},{"orig":5,"dest":56,"demand":78.63540993069407},{"orig":29,"dest":27,"demand":95.32256480181212},{"orig":6,"dest":29,"demand":29.39182219622865},{"orig":52,"dest":32,"demand":88.35487556033074},{"orig":33,"dest":41,"demand":59.93358535109857},{"orig":12,"dest":47,"demand":75.39223158687537},{"orig":63,"dest":30,"demand":48.37983785970233},{"orig":38,"dest":22,"demand":27.0394740766179},{"orig":53,"dest":30,"demand":15.665868254061564},{"orig":7,"dest":48,"demand":22.849952175620693},{"orig":62,"dest":5,"demand":15.304617189044338},{"orig":43,"dest":30,"demand":5.4104348857494555},{"orig":45,"dest":35,"demand":80.28548499281322},{"orig":16,"dest":25,"demand":32.81189990092782},{"orig":12,"dest":30,"demand":50.77074124999047},{"orig":59,"dest":30,"demand":49.075805045276454},{"orig":49,"dest":62,"demand":5.7111403973941},{"orig":11,"dest":63,"demand":27.91082271860935},{"orig":57,"dest":30,"demand":14.982754453529271},{"orig":24,"dest":58,"demand":10.107016465660662},{"orig":39,"dest":16,"demand":52.4882691007288},{"orig":48,"dest":13,"demand":74.43889264534997},{"orig":35,"dest":57,"demand":62.09854680523044},{"orig":30,"dest":13,"demand":66.72807889478118},{"orig":23,"dest":44,"demand":94.81306404356381},{"orig":33,"dest":44,"demand":98.89409847602798},{"orig":30,"dest":22,"demand":67.96806990806103},{"orig":33,"dest":38,"demand":55.83346249417785},{"orig":37,"dest":61,"demand":3.8344301820937616},{"orig":47,"dest":8,"demand":37.48648656356449},{"orig":16,"dest":30,"demand":42.41539035977217},{"orig":33,"dest":37,"demand":70.68626095235062},{"orig":30,"dest":9,"demand":96.192602176202},{"orig":30,"dest":25,"demand":1.707283127862928},{"orig":49,"dest":27,"demand":12.938418813070328},{"orig":7,"dest":30,"demand":72.94791428238882},{"orig":37,"dest":28,"demand":31.80557943359239},{"orig":48,"dest":15,"demand":57.88006677993944},{"orig":36,"dest":54,"demand":20.671945713388858},{"orig":21,"dest":30,"demand":15.130634366596125},{"orig":48,"dest":64,"demand":63.26041063190754},{"orig":25,"dest":8,"demand":78.98106679178963},{"orig":33,"dest":17,"demand":53.028752353877614},{"orig":52,"dest":60,"demand":61.175603983959554},{"orig":30,"dest":50,"demand":39.67252738551554},{"orig":1,"dest":55,"demand":83.69014909703269},{"orig":30,"dest":15,"demand":6.70601617159374},{"orig":30,"dest":58,"demand":44.77174281907044},{"orig":57,"dest":39,"demand":71.91470455556811},{"orig":59,"dest":43,"demand":84.04817668206348},{"orig":48,"dest":30,"demand":56.396632205826606},{"orig":59,"dest":40,"demand":24.00470506048725},{"orig":56,"dest":5,"demand":9.346894086925502},{"orig":15,"dest":58,"demand":35.941408316684594},{"orig":13,"dest":30,"demand":20.785465977785968},{"orig":26,"dest":30,"demand":65.44137877188095},{"orig":40,"dest":21,"demand":79.55979832917075},{"orig":2,"dest":56,"demand":31.18216049073652},{"orig":7,"dest":64,"demand":68.90870530555735},{"orig":44,"dest":19,"demand":41.217000291363135},{"orig":29,"dest":46,"demand":89.39624170546615},{"orig":24,"dest":38,"demand":24.677062366304693},{"orig":2,"dest":45,"demand":50.14951243736345},{"orig":7,"dest":17,"demand":14.596030943387612},{"orig":41,"dest":11,"demand":41.96302439801597},{"orig":37,"dest":8,"demand":96.8394929051026},{"orig":57,"dest":19,"demand":16.834131005054573},{"orig":2,"dest":38,"demand":30.279016831295994},{"orig":60,"dest":27,"demand":67.90326135907482},{"orig":44,"dest":31,"demand":29.371227936173078},{"orig":31,"dest":48,"demand":63.49008542241715},{"orig":49,"dest":54,"demand":63.878967573485966},{"orig":26,"dest":33,"demand":60.92273217065925},{"orig":61,"dest":10,"demand":87.75746594667916},{"orig":43,"dest":49,"demand":34.05305715782733},{"orig":9,"dest":43,"demand":11.375934616017593},{"orig":31,"dest":42,"demand":98.46510262573291},{"orig":58,"dest":36,"demand":13.670719121864026},{"orig":30,"dest":59,"demand":68.60124859821995},{"orig":18,"dest":15,"demand":5.04332959870307},{"orig":55,"dest":51,"demand":3.2812698717400974},{"orig":40,"dest":19,"demand":57.62952435767839},{"orig":17,"dest":10,"demand":65.86846313534868},{"orig":47,"dest":46,"demand":40.02468721695279},{"orig":5,"dest":62,"demand":34.58739794215394},{"orig":52,"dest":12,"demand":63.156405922135015},{"orig":38,"dest":42,"demand":23.796995326588142},{"orig":56,"dest":28,"demand":54.43852732208591},{"orig":46,"dest":62,"demand":60.365852920070836},{"orig":58,"dest":55,"demand":32.724436862469005},{"orig":55,"dest":37,"demand":21.340116931741843},{"orig":59,"dest":53,"demand":87.30717274053735},{"orig":43,"dest":17,"demand":28.036378374973637}]}}